polyfamily_tree/__init__.py
polyfamily_tree/errors.py
polyfamily_tree/family_member.py
polyfamily_tree/member_iterators.py
polyfamily_tree-0.1.0.dist-info/LICENSE
polyfamily_tree-0.1.0.dist-info/METADATA
polyfamily_tree-0.1.0.dist-info/WHEEL
polyfamily_tree-0.1.0.dist-info/top_level.txt
polyfamily_tree-0.1.0.dist-info/RECORD
