Metadata-Version: 2.1
Name: polyfamily-tree
Version: 0.1.0
Summary: Python package for structuredly managing directional relationship between objects.
Home-page: https://github.com/grasshopperTrainer/polyfamily_tree
Author: grasshopperTrainer
Author-email: grasshoppertrainer@gmail.com
License: UNKNOWN
Keywords: DAG,directed,acyclic,graph
Platform: UNKNOWN
Classifier: Development Status :: 3 - Alpha
Classifier: License :: OSI Approved :: MIT License
Classifier: Operating System :: OS Independent
Requires-Python: >=3
